diracx/testing/__init__.py
diracx/testing/__main__.py
diracx/testing/client_generation.py
diracx/testing/client_generation_pytest.py
diracx/testing/dummy_osdb.py
diracx/testing/entrypoints.py
diracx/testing/mock_osdb.py
diracx/testing/osdb.py
diracx/testing/routers.py
diracx/testing/time.py
diracx/testing/utils.py
diracx/testing/scripts/collect_demo_coverage.sh
diracx_testing-0.0.7.dist-info/METADATA
diracx_testing-0.0.7.dist-info/WHEEL
diracx_testing-0.0.7.dist-info/RECORD
