Metadata-Version: 2.4
Name: diracx-testing
Version: 0.0.7
Summary: TODO
License: GPL-3.0-only
Classifier: Intended Audience :: Science/Research
Classifier: License :: OSI Approved :: GNU General Public License v3 (GPLv3)
Classifier: Programming Language :: Python :: 3
Classifier: Topic :: Scientific/Engineering
Classifier: Topic :: System :: Distributed Computing
Requires-Python: >=3.11
Requires-Dist: httpx
Requires-Dist: joserfc
Requires-Dist: pytest
Requires-Dist: pytest-asyncio==1.0.0
Requires-Dist: pytest-cov
Requires-Dist: pytest-github-actions-annotate-failures
Requires-Dist: pytest-xdist
Requires-Dist: uuid-utils
Provides-Extra: testing
